stepuplib/__init__.py
stepuplib/arth.py
stepuplib/title.py
steplib-3.0.dist-info/METADATA
steplib-3.0.dist-info/WHEEL
steplib-3.0.dist-info/top_level.txt
steplib-3.0.dist-info/RECORD
