Metadata-Version: 2.1
Name: steplib
Version: 3.0
Summary: find sum of 3 numbers
Home-page: UNKNOWN
Author: stepup
License: MIT
Platform: UNKNOWN
